plsline/__init__.py
plsline/__main__.py
plsline/plsline.py
plsline-0.0.1.dist-info/licenses/LICENSE
plsline-0.0.1.dist-info/METADATA
plsline-0.0.1.dist-info/WHEEL
plsline-0.0.1.dist-info/top_level.txt
plsline-0.0.1.dist-info/RECORD
