Metadata-Version: 2.4
Name: plsline
Version: 0.0.1
Summary: Add decoration to print
Author: Tanaka Kimito
License: MIT
Project-URL: github, https://github.com/KimitoTanaka/PlsLine
Project-URL: README, https://github.com/KimitoTanaka/PlsLine/blob/main/README.md
Classifier: Programming Language :: Python :: 3
Classifier: Programming Language :: Python :: 3.8
Classifier: Programming Language :: Python :: 3.9
Classifier: Programming Language :: Python :: 3.10
Classifier: Programming Language :: Python :: 3.11
Classifier: Programming Language :: Python :: 3.12
Classifier: Programming Language :: Python :: 3.13
Classifier: Operating System :: Microsoft :: Windows
Classifier: License :: OSI Approved :: MIT License
Requires-Python: >=3.8
License-File: LICENSE
Dynamic: license-file
